AISTLAB_utils-0.1.6.dist-info/DESCRIPTION.rst
AISTLAB_utils-0.1.6.dist-info/METADATA
AISTLAB_utils-0.1.6.dist-info/RECORD
AISTLAB_utils-0.1.6.dist-info/WHEEL
AISTLAB_utils-0.1.6.dist-info/entry_points.txt
AISTLAB_utils-0.1.6.dist-info/metadata.json
AISTLAB_utils-0.1.6.dist-info/top_level.txt
aist_utils/AIST.py
aist_utils/AISTLAB.py
aist_utils/__init__.py
aist_utils/creo.py
