Metadata-Version: 2.0
Name: AISTLAB-utils
Version: 0.1.6
Summary: Tools packages created by python.
Home-page: https://github.com/winxos/AIST_utils
Author: winxos
Author-email: winxos@hotmail.com
License: MIT License
Download-URL: https://github.com/winxos/AISTLAB_utils
Keywords: utils,winxos,AISTLAB
Platform: UNKNOWN
Classifier: Development Status :: 3 - Alpha
Classifier: Topic :: Utilities
Classifier: Programming Language :: Python :: 3
Classifier: Programming Language :: Python :: 3.2
Classifier: Programming Language :: Python :: 3.3
Classifier: Programming Language :: Python :: 3.4
Classifier: Programming Language :: Python :: 3.5
Classifier: Programming Language :: Python :: 3.6
